{
  "critical_fields": {
    "Email": "fldNiWIBmDRON3QGF",
    "Phone": "fldPgDn3NiFexisIh",
    "Processing Status": "fldAVrpORl3DMqTYu",
    "Kajabi Tags": "fldQ7UAfiMzqgY1W9",
    "Last Reply At": "fld2WzCrDL3l1WA5b",
    "Last Reply Text": "fldXwlhQMJZGXMVJ9",
    "Engagement - Total Score": "fldyZMljoLlB3BeYK",
    "Engagement - Level": "fldspSLdnQCFuFe1Z",
    "Engagement - Tag Count": "fldtVtnFREvHKDnVT",
    "Engagement - Recency Points": "fldYglpx4UtiXa1nW",
    "Conversation Status": "fldBY5Tp54mJsExrW"
  }
}
